kodijsonrpc/__init__.py
kodijsonrpc/kodijsonrpc.py
kodijsonrpc-1.1.dist-info/LICENSE.md
kodijsonrpc-1.1.dist-info/METADATA
kodijsonrpc-1.1.dist-info/WHEEL
kodijsonrpc-1.1.dist-info/top_level.txt
kodijsonrpc-1.1.dist-info/RECORD
