Metadata-Version: 2.1
Name: kodijsonrpc
Version: 1.1
Summary: Kodi JSON-RPC client
Home-page: http://github.com/davgeo/kodijsonrpc
Author: David George
Author-email: dcg.git@gmail.com
License: MIT
Platform: UNKNOWN
Requires-Dist: jsonrpcclient (==2.0.1)
Requires-Dist: requests (==2.20.0)
